__init__.py
optional_requirements/__init__.py
optional_requirements/_errors.py
optional_requirements/_import.py
optional_requirements/_module_info.py
optional_requirements/_requirements.py
optional_requirements/_requirements_file.py
optional_requirements/py.typed
optional_requirements/version.py
optional_requirements-0.0.2.dist-info/LICENSE
optional_requirements-0.0.2.dist-info/METADATA
optional_requirements-0.0.2.dist-info/WHEEL
optional_requirements-0.0.2.dist-info/top_level.txt
optional_requirements-0.0.2.dist-info/RECORD
