Metadata-Version: 2.1
Name: optional_requirements
Version: 0.0.2
Summary: Manage optional requirements and their versions at runtime
Author-email: Rudolf Byker <rudolfbyker@gmail.com>
Project-URL: repository, https://github.com/AutoActuary/optional_requirements
Classifier: Programming Language :: Python :: 3
Classifier: License :: Other/Proprietary License
Classifier: Operating System :: OS Independent
Requires-Python: >=3.11
License-File: LICENSE
Requires-Dist: packaging ==24.*
